explainable_robotics/__init__.py
explainable_robotics/cli.py
explainable_robotics/demo.py
explainable_robotics/main.py
explainable_robotics/config/default.yaml
explainable_robotics-0.1.0.dist-info/LICENSE
explainable_robotics-0.1.0.dist-info/METADATA
explainable_robotics-0.1.0.dist-info/WHEEL
explainable_robotics-0.1.0.dist-info/entry_points.txt
explainable_robotics-0.1.0.dist-info/top_level.txt
explainable_robotics-0.1.0.dist-info/RECORD
