Metadata-Version: 2.2
Name: explainable-robotics
Version: 0.1.0
Summary: 神経科学的に妥当なヒューマノイドロボット制御のための説明可能AIフレームワーク
Home-page: https://github.com/zapabob/explainable_robotics
Author: Ryo Minegishi
Author-email: Ryo Minegishi <info@explainable-robotics.com>
License: MIT License
Project-URL: homepage, https://github.com/zapabob/explainable_robotics
Project-URL: repository, https://github.com/zapabob/explainable_robotics
Requires-Python: >=3.12
License-File: LICENSE
Provides-Extra: dev
Requires-Dist: pytest>=7.0.0; extra == "dev"
Requires-Dist: black>=23.0.0; extra == "dev"
Requires-Dist: flake8>=6.0.0; extra == "dev"
Requires-Dist: isort>=5.12.0; extra == "dev"
Requires-Dist: mypy>=1.0.0; extra == "dev"
Requires-Dist: sphinx>=6.0.0; extra == "dev"
Requires-Dist: sphinx-rtd-theme>=1.2.0; extra == "dev"
Dynamic: author
Dynamic: home-page
Dynamic: requires-python
